LICENSE.txt
MANIFEST.in
README.rst
setup.py
obpds.egg-info/PKG-INFO
obpds.egg-info/SOURCES.txt
obpds.egg-info/dependency_links.txt
obpds.egg-info/requires.txt
obpds.egg-info/top_level.txt
src/obpds/__init__.py
src/obpds/config.py
src/obpds/contact.py
src/obpds/device.py
src/obpds/layer.py
src/obpds/material.py
src/obpds/newton.py
src/obpds/solution.py
src/obpds/solver.py
src/obpds/units.py
src/obpds/version.py
src/obpds/examples/__init__.py
src/obpds/examples/cv_pn_diode.py
src/obpds/examples/cv_schottky_diode.py
src/obpds/examples/degenerate_pn_diode.py
src/obpds/examples/in_schottky_diode.py
src/obpds/examples/interactive_np_diode.py
src/obpds/examples/interactive_pn_diode.py
src/obpds/examples/interactive_schottky_diode.py
src/obpds/examples/ip_schottky_diode.py
src/obpds/examples/np_diode.py
src/obpds/examples/pin_diode.py
src/obpds/examples/pn_diode.py
src/obpds/examples/pn_graded_hj_diode.py
src/obpds/examples/pn_hj_diode.py
src/obpds/examples/schottky_diode.py
src/obpds/tests/__init__.py
src/obpds/tests/__main__.py
src/obpds/tests/test_obpds.py