Metadata-Version: 1.0
Name: obpds
Version: 0.1.2
Summary: free, open-source technology computer aided design software for simulating semiconductor structures and devices
Home-page: http://scott-maddox.github.io/obpds
Author: Scott J. Maddox
Author-email: smaddox@utexas.edu
License: AGPLv3
Platform: UNKNOWN
